{
    "autoAdd": true,
    "autoJoin": true,
    "autoJoinTicket": false,
    "autoLeave": true,
    "autoRead": true,
    "blacklist": {
        "uf6b0fecdf26459e6a48b5a387c1144d2": true
    },
    "canceljoin": false,
    "cancelprotect": false,
    "changeGroupPicture": {},
    "changePicture": {},
    "checkSticker": false,
    "datectMention": true,
    "dblack": false,
    "dblacklist": false,
    "detectMention": false,
    "inviteprotect": false,
    "keyCommand": "",
    "kickjoin": false,
    "lang": "JP",
    "mimic": {
        "copy": false,
        "status": true,
        "target": {
            "u0f18348d27489c14ef0da1db3b46f981": true,
            "u10977625581e67dcce5db8ea66732b86": true,
            "u177e060ff19b1bf4c5bb45ca2f3904fc": true,
            "u1c4c0167801aeacd4174e45d22ab3972": true,
            "u1d97813a738df10812e29e4be6d9ebb2": true,
            "u297d14a074a7252344b4f7aa195a3111": true,
            "u58395e5e31e8b975f3e9ad1ce1c7e188": true,
            "u5974316c39660e5918e7a8930f3b3693": true,
            "u7db9ac667be42ff8350e3bd6eacea1d5": true,
            "ucf9951cca797709b8a2bca18941740f2": true,
            "ucfe3dd28905ea3c7e987d98ccb45ad6c": true
        }
    },
    "protect": false,
    "qrprotect": false,
    "userAgent": [
        "Mozilla/5.0 (X11; U; Linux i586; de; rv:5.0) Gecko/20100101 Firefox/5.0",
        "Mozilla/5.0 (X11; U; Linux amd64; rv:5.0) Gecko/20100101 Firefox/5.0 (Debian)",
        "Mozilla/5.0 (X11; U; Linux amd64; en-US; rv:5.0) Gecko/20110619 Firefox/5.0",
        "Mozilla/5.0 (X11; Linux) Gecko Firefox/5.0",
        "Mozilla/5.0 (X11; Linux x86_64; rv:5.0) Gecko/20100101 Firefox/5.0 FirePHP/0.5",
        "Mozilla/5.0 (X11; Linux x86_64; rv:5.0) Gecko/20100101 Firefox/5.0 Firefox/5.0",
        "Mozilla/5.0 (X11; Linux x86_64) Gecko Firefox/5.0",
        "Mozilla/5.0 (X11; Linux ppc; rv:5.0) Gecko/20100101 Firefox/5.0",
        "Mozilla/5.0 (X11; Linux AMD64) Gecko Firefox/5.0",
        "Mozilla/5.0 (X11; FreeBSD amd64; rv:5.0) Gecko/20100101 Firefox/5.0",
        "Mozilla/5.0 (Windows NT 6.2; WOW64; rv:5.0) Gecko/20100101 Firefox/5.0",
        "Mozilla/5.0 (Windows NT 6.1; Win64; x64; rv:5.0) Gecko/20110619 Firefox/5.0",
        "Mozilla/5.0 (Windows NT 6.1; Win64; x64; rv:5.0) Gecko/20100101 Firefox/5.0",
        "Mozilla/5.0 (Windows NT 6.1; rv:6.0) Gecko/20100101 Firefox/5.0",
        "Mozilla/5.0 (Windows NT 6.1.1; rv:5.0) Gecko/20100101 Firefox/5.0",
        "Mozilla/5.0 (Windows NT 5.2; WOW64; rv:5.0) Gecko/20100101 Firefox/5.0",
        "Mozilla/5.0 (Windows NT 5.1; U; rv:5.0) Gecko/20100101 Firefox/5.0",
        "Mozilla/5.0 (Windows NT 5.1; rv:2.0.1) Gecko/20100101 Firefox/5.0",
        "Mozilla/5.0 (Windows NT 5.0; WOW64; rv:5.0) Gecko/20100101 Firefox/5.0",
        "Mozilla/5.0 (Windows NT 5.0; rv:5.0) Gecko/20100101 Firefox/5.0"
    ],
    "wblack": false,
    "wblacklist": false
}